wagtail_oauth2-2.0.6.dist-info/METADATA
wagtail_oauth2-2.0.6.dist-info/WHEEL
wagtail_oauth2-2.0.6.dist-info/entry_points.txt
wagtail_oauth2-2.0.6.dist-info/licenses/LICENSE
wagtail_oauth2/__init__.py
wagtail_oauth2/resources.py
wagtail_oauth2/settings.py
wagtail_oauth2/templates/login_error.html
wagtail_oauth2/urls.py
wagtail_oauth2/utils.py
wagtail_oauth2/views.py
wagtail_oauth2-2.0.6.dist-info/RECORD
