Metadata-Version: 2.1
Name: wagtail-oauth2
Version: 2.0.6
Summary: OAuth2.0 authentication fo wagtail
Author-Email: Guillaume Gauvrit <guillaume@gandi.net>
License: BSD-Derived
Classifier: Intended Audience :: Developers
Classifier: Topic :: Software Development :: Libraries :: Python Modules
Classifier: Topic :: Internet :: WWW/HTTP
Classifier: Framework :: Wagtail
Classifier: Framework :: Wagtail :: 4
Classifier: Framework :: Wagtail :: 5
Classifier: Framework :: Wagtail :: 6
Classifier: Framework :: Wagtail :: 7
Classifier: License :: OSI Approved :: BSD License
Project-URL: homepage, https://wagtail-oauth2.readthedocs.io/en/latest/
Project-URL: repository, https://github.com/Gandi/wagtail-oauth2
Requires-Python: <4.0,>=3.7
Requires-Dist: Django<5,>=3.2.0
Requires-Dist: wagtail<8,>=4.0
Requires-Dist: requests<3,>=2.26.0
Provides-Extra: docs
Requires-Dist: sphinx>=9.0.0; python_version >= "3.12" and extra == "docs"
Requires-Dist: furo>=2025.12.19; python_version >= "3.12" and extra == "docs"
